{"sections":[],"identifier":{"url":"doc:\/\/Boutique\/documentation\/Boutique\/AsyncStoredValue","interfaceLanguage":"swift"},"variants":[{"paths":["\/documentation\/boutique\/asyncstoredvalue"],"traits":[{"interfaceLanguage":"swift"}]}],"abstract":[{"text":"The @","type":"text"},{"identifier":"doc:\/\/Boutique\/documentation\/Boutique\/AsyncStoredValue","isActive":true,"type":"reference"},{"type":"text","text":" property wrapper to automagically persist a single "},{"type":"codeVoice","code":"Item"},{"type":"text","text":" in a "},{"type":"codeVoice","code":"StorageEngine"},{"text":" ","type":"text"},{"text":"rather than an array of items that would be persisted in a ","type":"text"},{"type":"reference","isActive":true,"identifier":"doc:\/\/Boutique\/documentation\/Boutique\/Store"},{"text":" or using @","type":"text"},{"type":"reference","identifier":"doc:\/\/Boutique\/documentation\/Boutique\/Stored","isActive":true},{"type":"text","text":"."}],"primaryContentSections":[{"declarations":[{"platforms":["macOS"],"tokens":[{"text":"@","kind":"attribute"},{"preciseIdentifier":"s:ScM","text":"MainActor","kind":"attribute"},{"text":" ","kind":"text"},{"text":"@propertyWrapper","kind":"attribute"},{"kind":"text","text":" "},{"text":"struct","kind":"keyword"},{"text":" ","kind":"text"},{"text":"AsyncStoredValue","kind":"identifier"},{"text":"<","kind":"text"},{"kind":"genericParameter","text":"Item"},{"text":"> ","kind":"text"},{"text":"where","kind":"keyword"},{"kind":"text","text":" "},{"kind":"typeIdentifier","text":"Item"},{"kind":"text","text":" : "},{"text":"Decodable","preciseIdentifier":"s:Se","kind":"typeIdentifier"},{"kind":"text","text":", "},{"text":"Item","kind":"typeIdentifier"},{"text":" : ","kind":"text"},{"text":"Encodable","kind":"typeIdentifier","preciseIdentifier":"s:SE"},{"text":", ","kind":"text"},{"kind":"typeIdentifier","text":"Item"},{"kind":"text","text":" : "},{"text":"Equatable","kind":"typeIdentifier","preciseIdentifier":"s:SQ"}],"languages":["swift"]}],"kind":"declarations"},{"kind":"content","content":[{"level":2,"anchor":"overview","text":"Overview","type":"heading"},{"type":"paragraph","inlineContent":[{"type":"text","text":"You should use an @"},{"identifier":"doc:\/\/Boutique\/documentation\/Boutique\/AsyncStoredValue","type":"reference","isActive":true},{"text":" if you’re only storing a single item, as opposed to a @","type":"text"},{"isActive":true,"identifier":"doc:\/\/Boutique\/documentation\/Boutique\/Store","type":"reference"},{"text":" ","type":"text"},{"type":"text","text":"which stores an array of items exposed as the "},{"code":"items: [Item]","type":"codeVoice"},{"type":"text","text":" property."}]},{"inlineContent":[{"type":"text","text":"This is useful for similar use cases as "},{"type":"codeVoice","code":"UserDefaults"},{"text":", where it’s common to store only a single item","type":"text"},{"text":" ","type":"text"},{"type":"text","text":"such as the app’s "},{"type":"codeVoice","code":"lastOpenedDate"},{"type":"text","text":", an object of the user’s preferences, configurations, and more."}],"type":"paragraph"},{"type":"paragraph","inlineContent":[{"text":"Results are delivered asynchronously so you cannot depend on this value to be available on-demand.","type":"text"},{"type":"text","text":" "},{"type":"strong","inlineContent":[{"type":"text","text":"If you need to access a value at app launch you should consider using"}]},{"type":"text","text":" "},{"isActive":true,"type":"reference","identifier":"doc:\/\/Boutique\/documentation\/Boutique\/StoredValue"},{"text":" which has","type":"text"},{"type":"text","text":" "},{"type":"text","text":"the same API but stores data into "},{"code":"UserDefaults","type":"codeVoice"},{"text":".","type":"text"}]},{"type":"paragraph","inlineContent":[{"type":"text","text":"You must initialize an @"},{"type":"reference","identifier":"doc:\/\/Boutique\/documentation\/Boutique\/AsyncStoredValue","isActive":true},{"type":"text","text":" with a default value like you would any other Swift property."}]},{"code":["@AsyncStoredValue(storage: SQLiteStorageEngine.default(appendingPath: \"RedPandaStorage\"))","private var redPanda = RedPanda(cuteRating: 100)"],"type":"codeListing","syntax":null},{"type":"paragraph","inlineContent":[{"type":"text","text":"An @"},{"type":"reference","isActive":true,"identifier":"doc:\/\/Boutique\/documentation\/Boutique\/AsyncStoredValue"},{"type":"text","text":" can be nullable but in that case you will have to specify the type as well."}]},{"syntax":null,"code":["@AsyncStoredValue<RedPanda?>(storage: SQLiteStorageEngine.default(appendingPath: \"SpanishRedPandaStorage\"))","private var spanishRedPanda = nil"],"type":"codeListing"},{"inlineContent":[{"type":"text","text":"Using @"},{"identifier":"doc:\/\/Boutique\/documentation\/Boutique\/AsyncStoredValue","isActive":true,"type":"reference"},{"text":" is also straightforward, there are only two functions.","type":"text"},{"type":"text","text":" "},{"text":"To change the value of the @","type":"text"},{"identifier":"doc:\/\/Boutique\/documentation\/Boutique\/AsyncStoredValue","type":"reference","isActive":true},{"type":"text","text":", you can use the "},{"isActive":true,"identifier":"doc:\/\/Boutique\/documentation\/Boutique\/AsyncStoredValue\/set(_:)","type":"reference"},{"type":"text","text":" and "},{"identifier":"doc:\/\/Boutique\/documentation\/Boutique\/AsyncStoredValue\/reset()","type":"reference","isActive":true},{"type":"text","text":" functions."}],"type":"paragraph"},{"syntax":null,"type":"codeListing","code":["$redPanda.set(RedPanda(cuteRating: 99)) \/\/ The @AsyncStoredValue has a new red panda","$redPanda.reset() \/\/ The @AsyncStoredValue is nil"]},{"type":"paragraph","inlineContent":[{"text":"One last bit of advice, when calling ","type":"text"},{"isActive":true,"type":"reference","identifier":"doc:\/\/Boutique\/documentation\/Boutique\/AsyncStoredValue\/set(_:)"},{"type":"text","text":" and "},{"isActive":true,"identifier":"doc:\/\/Boutique\/documentation\/Boutique\/AsyncStoredValue\/reset()","type":"reference"},{"text":" don’t forget to put a ","type":"text"},{"type":"codeVoice","code":"$"},{"type":"text","text":" "},{"type":"text","text":"in front of the the "},{"type":"codeVoice","code":"$storedValue"},{"type":"text","text":"."}]},{"type":"paragraph","inlineContent":[{"type":"text","text":"See: "},{"isActive":true,"type":"reference","identifier":"doc:\/\/Boutique\/documentation\/Boutique\/AsyncStoredValue\/set(_:)"},{"type":"text","text":" and "},{"type":"reference","identifier":"doc:\/\/Boutique\/documentation\/Boutique\/AsyncStoredValue\/reset()","isActive":true},{"type":"text","text":" docs for a more in depth explanation."}]}]}],"topicSections":[{"title":"Initializers","identifiers":["doc:\/\/Boutique\/documentation\/Boutique\/AsyncStoredValue\/init(wrappedValue:storage:)"]},{"title":"Instance Properties","identifiers":["doc:\/\/Boutique\/documentation\/Boutique\/AsyncStoredValue\/binding","doc:\/\/Boutique\/documentation\/Boutique\/AsyncStoredValue\/projectedValue","doc:\/\/Boutique\/documentation\/Boutique\/AsyncStoredValue\/publisher","doc:\/\/Boutique\/documentation\/Boutique\/AsyncStoredValue\/wrappedValue"]},{"title":"Instance Methods","identifiers":["doc:\/\/Boutique\/documentation\/Boutique\/AsyncStoredValue\/append(_:)","doc:\/\/Boutique\/documentation\/Boutique\/AsyncStoredValue\/reset()","doc:\/\/Boutique\/documentation\/Boutique\/AsyncStoredValue\/set(_:)","doc:\/\/Boutique\/documentation\/Boutique\/AsyncStoredValue\/toggle()","doc:\/\/Boutique\/documentation\/Boutique\/AsyncStoredValue\/togglePresence(_:)","doc:\/\/Boutique\/documentation\/Boutique\/AsyncStoredValue\/update(key:value:)"]}],"relationshipsSections":[{"identifiers":["doc:\/\/Boutique\/s8SendableP"],"title":"Conforms To","type":"conformsTo","kind":"relationships"}],"hierarchy":{"paths":[["doc:\/\/Boutique\/documentation\/Boutique"]]},"kind":"symbol","metadata":{"externalID":"s:8Boutique16AsyncStoredValueV","title":"AsyncStoredValue","navigatorTitle":[{"kind":"identifier","text":"AsyncStoredValue"}],"symbolKind":"struct","roleHeading":"Structure","modules":[{"name":"Boutique"}],"role":"symbol","fragments":[{"kind":"keyword","text":"struct"},{"text":" ","kind":"text"},{"text":"AsyncStoredValue","kind":"identifier"}]},"schemaVersion":{"patch":0,"major":0,"minor":3},"references":{"doc://Boutique/documentation/Boutique/AsyncStoredValue/publisher":{"url":"\/documentation\/boutique\/asyncstoredvalue\/publisher","title":"publisher","role":"symbol","kind":"symbol","type":"topic","abstract":[{"type":"text","text":"A Combine publisher that allows you to observe any changes to the @"},{"type":"reference","identifier":"doc:\/\/Boutique\/documentation\/Boutique\/AsyncStoredValue","isActive":true},{"text":".","type":"text"}],"fragments":[{"text":"var","kind":"keyword"},{"text":" ","kind":"text"},{"text":"publisher","kind":"identifier"},{"kind":"text","text":": "},{"text":"AnyPublisher","kind":"typeIdentifier","preciseIdentifier":"s:7Combine12AnyPublisherV"},{"kind":"text","text":"<"},{"kind":"typeIdentifier","text":"Item"},{"text":", ","kind":"text"},{"text":"Never","kind":"typeIdentifier","preciseIdentifier":"s:s5NeverO"},{"text":">","kind":"text"}],"identifier":"doc:\/\/Boutique\/documentation\/Boutique\/AsyncStoredValue\/publisher"},"doc://Boutique/documentation/Boutique":{"title":"Boutique","kind":"symbol","identifier":"doc:\/\/Boutique\/documentation\/Boutique","role":"collection","abstract":[{"type":"text","text":"A simple but surprisingly fancy data store and so much more"}],"type":"topic","url":"\/documentation\/boutique"},"doc://Boutique/documentation/Boutique/AsyncStoredValue":{"kind":"symbol","url":"\/documentation\/boutique\/asyncstoredvalue","navigatorTitle":[{"text":"AsyncStoredValue","kind":"identifier"}],"type":"topic","title":"AsyncStoredValue","abstract":[{"type":"text","text":"The @"},{"identifier":"doc:\/\/Boutique\/documentation\/Boutique\/AsyncStoredValue","isActive":true,"type":"reference"},{"text":" property wrapper to automagically persist a single ","type":"text"},{"type":"codeVoice","code":"Item"},{"type":"text","text":" in a "},{"code":"StorageEngine","type":"codeVoice"},{"type":"text","text":" "},{"text":"rather than an array of items that would be persisted in a ","type":"text"},{"isActive":true,"identifier":"doc:\/\/Boutique\/documentation\/Boutique\/Store","type":"reference"},{"text":" or using @","type":"text"},{"isActive":true,"identifier":"doc:\/\/Boutique\/documentation\/Boutique\/Stored","type":"reference"},{"type":"text","text":"."}],"role":"symbol","identifier":"doc:\/\/Boutique\/documentation\/Boutique\/AsyncStoredValue","fragments":[{"kind":"keyword","text":"struct"},{"text":" ","kind":"text"},{"kind":"identifier","text":"AsyncStoredValue"}]},"doc://Boutique/documentation/Boutique/AsyncStoredValue/update(key:value:)":{"fragments":[{"kind":"keyword","text":"func"},{"text":" ","kind":"text"},{"text":"update","kind":"identifier"},{"text":"<","kind":"text"},{"text":"Key","kind":"genericParameter"},{"kind":"text","text":", "},{"text":"Value","kind":"genericParameter"},{"kind":"text","text":">("},{"text":"key","kind":"externalParam"},{"text":": ","kind":"text"},{"kind":"typeIdentifier","text":"Key"},{"text":", ","kind":"text"},{"kind":"externalParam","text":"value"},{"text":": ","kind":"text"},{"text":"Value","kind":"typeIdentifier"},{"kind":"text","text":"?) "},{"kind":"keyword","text":"async"},{"text":" ","kind":"text"},{"kind":"keyword","text":"throws"}],"kind":"symbol","identifier":"doc:\/\/Boutique\/documentation\/Boutique\/AsyncStoredValue\/update(key:value:)","type":"topic","title":"update(key:value:)","url":"\/documentation\/boutique\/asyncstoredvalue\/update(key:value:)","role":"symbol","conformance":{"availabilityPrefix":[{"type":"text","text":"Available when"}],"conformancePrefix":[{"type":"text","text":"Conforms when"}],"constraints":[{"type":"codeVoice","code":"Item"},{"type":"text","text":" conforms to "},{"code":"Decodable","type":"codeVoice"},{"type":"text","text":", "},{"type":"codeVoice","code":"Encodable"},{"type":"text","text":", and "},{"type":"codeVoice","code":"Equatable"},{"text":".","type":"text"}]},"abstract":[{"type":"text","text":"A function to set an @"},{"isActive":true,"type":"reference","identifier":"doc:\/\/Boutique\/documentation\/Boutique\/AsyncStoredValue"},{"type":"text","text":" represented by a "},{"type":"codeVoice","code":"Dictionary"},{"type":"text","text":" "},{"text":"without having to manually make an intermediate copy for every value update.","type":"text"}]},"doc://Boutique/documentation/Boutique/AsyncStoredValue/binding":{"title":"binding","url":"\/documentation\/boutique\/asyncstoredvalue\/binding","role":"symbol","conformance":{"conformancePrefix":[{"type":"text","text":"Conforms when"}],"availabilityPrefix":[{"text":"Available when","type":"text"}],"constraints":[{"type":"codeVoice","code":"Item"},{"text":" conforms to ","type":"text"},{"code":"Decodable","type":"codeVoice"},{"type":"text","text":", "},{"type":"codeVoice","code":"Encodable"},{"text":", and ","type":"text"},{"code":"Equatable","type":"codeVoice"},{"type":"text","text":"."}]},"kind":"symbol","type":"topic","abstract":[{"text":"A convenient way to create a ","type":"text"},{"code":"Binding","type":"codeVoice"},{"text":" from an ","type":"text"},{"code":"AsyncStoredValue","type":"codeVoice"},{"text":".","type":"text"}],"fragments":[{"kind":"keyword","text":"var"},{"text":" ","kind":"text"},{"text":"binding","kind":"identifier"},{"text":": ","kind":"text"},{"kind":"typeIdentifier","preciseIdentifier":"s:7SwiftUI7BindingV","text":"Binding"},{"kind":"text","text":"<"},{"kind":"typeIdentifier","text":"Item"},{"text":">","kind":"text"}],"identifier":"doc:\/\/Boutique\/documentation\/Boutique\/AsyncStoredValue\/binding"},"doc://Boutique/s8SendableP":{"type":"unresolvable","title":"Swift.Sendable","identifier":"doc:\/\/Boutique\/s8SendableP"},"doc://Boutique/documentation/Boutique/Stored":{"fragments":[{"kind":"keyword","text":"struct"},{"text":" ","kind":"text"},{"text":"Stored","kind":"identifier"}],"identifier":"doc:\/\/Boutique\/documentation\/Boutique\/Stored","url":"\/documentation\/boutique\/stored","navigatorTitle":[{"text":"Stored","kind":"identifier"}],"type":"topic","role":"symbol","kind":"symbol","abstract":[{"text":"The @","type":"text"},{"identifier":"doc:\/\/Boutique\/documentation\/Boutique\/Stored","isActive":true,"type":"reference"},{"type":"text","text":" property wrapper to automagically initialize a "},{"identifier":"doc:\/\/Boutique\/documentation\/Boutique\/Store","type":"reference","isActive":true},{"text":".","type":"text"}],"title":"Stored"},"doc://Boutique/documentation/Boutique/AsyncStoredValue/init(wrappedValue:storage:)":{"url":"\/documentation\/boutique\/asyncstoredvalue\/init(wrappedvalue:storage:)","title":"init(wrappedValue:storage:)","role":"symbol","kind":"symbol","type":"topic","abstract":[{"type":"text","text":"Initializes an @"},{"type":"reference","identifier":"doc:\/\/Boutique\/documentation\/Boutique\/AsyncStoredValue","isActive":true},{"type":"text","text":"."}],"fragments":[{"kind":"identifier","text":"init"},{"kind":"text","text":"("},{"text":"wrappedValue","kind":"externalParam"},{"kind":"text","text":": "},{"text":"Item","kind":"typeIdentifier"},{"text":", ","kind":"text"},{"text":"storage","kind":"externalParam"},{"text":": any ","kind":"text"},{"kind":"typeIdentifier","text":"StorageEngine","preciseIdentifier":"s:6Bodega13StorageEngineP"},{"text":")","kind":"text"}],"identifier":"doc:\/\/Boutique\/documentation\/Boutique\/AsyncStoredValue\/init(wrappedValue:storage:)"},"doc://Boutique/documentation/Boutique/AsyncStoredValue/reset()":{"fragments":[{"text":"func","kind":"keyword"},{"kind":"text","text":" "},{"kind":"identifier","text":"reset"},{"kind":"text","text":"() "},{"text":"async","kind":"keyword"},{"text":" ","kind":"text"},{"kind":"keyword","text":"throws"}],"identifier":"doc:\/\/Boutique\/documentation\/Boutique\/AsyncStoredValue\/reset()","url":"\/documentation\/boutique\/asyncstoredvalue\/reset()","type":"topic","kind":"symbol","role":"symbol","abstract":[{"type":"text","text":"Resets the @"},{"isActive":true,"identifier":"doc:\/\/Boutique\/documentation\/Boutique\/AsyncStoredValue","type":"reference"},{"type":"text","text":" to the default value."}],"title":"reset()"},"doc://Boutique/documentation/Boutique/AsyncStoredValue/append(_:)":{"identifier":"doc:\/\/Boutique\/documentation\/Boutique\/AsyncStoredValue\/append(_:)","abstract":[{"type":"text","text":"A function to append a @"},{"identifier":"doc:\/\/Boutique\/documentation\/Boutique\/StoredValue","type":"reference","isActive":true},{"text":" represented by an ","type":"text"},{"type":"codeVoice","code":"Array"},{"type":"text","text":" "},{"type":"text","text":"without having to manually make an intermediate copy for every value update."}],"role":"symbol","fragments":[{"kind":"keyword","text":"func"},{"text":" ","kind":"text"},{"kind":"identifier","text":"append"},{"text":"(","kind":"text"},{"text":"Item","kind":"typeIdentifier"},{"kind":"text","text":"."},{"text":"Element","kind":"typeIdentifier","preciseIdentifier":"s:ST7ElementQa"},{"kind":"text","text":") "},{"text":"async","kind":"keyword"},{"kind":"text","text":" "},{"text":"throws","kind":"keyword"}],"conformance":{"constraints":[{"code":"Item","type":"codeVoice"},{"text":" conforms to ","type":"text"},{"code":"Decodable","type":"codeVoice"},{"text":", ","type":"text"},{"type":"codeVoice","code":"Encodable"},{"text":", ","type":"text"},{"code":"Equatable","type":"codeVoice"},{"type":"text","text":", and "},{"type":"codeVoice","code":"RangeReplaceableCollection"},{"text":".","type":"text"}],"conformancePrefix":[{"type":"text","text":"Conforms when"}],"availabilityPrefix":[{"type":"text","text":"Available when"}]},"kind":"symbol","url":"\/documentation\/boutique\/asyncstoredvalue\/append(_:)","type":"topic","title":"append(_:)"},"doc://Boutique/documentation/Boutique/AsyncStoredValue/toggle()":{"fragments":[{"text":"func","kind":"keyword"},{"kind":"text","text":" "},{"text":"toggle","kind":"identifier"},{"text":"() ","kind":"text"},{"text":"async","kind":"keyword"},{"kind":"text","text":" "},{"kind":"keyword","text":"throws"}],"abstract":[{"type":"text","text":"A function to toggle an @"},{"isActive":true,"type":"reference","identifier":"doc:\/\/Boutique\/documentation\/Boutique\/AsyncStoredValue"},{"type":"text","text":" that represent a "},{"code":"Bool","type":"codeVoice"},{"text":".","type":"text"}],"identifier":"doc:\/\/Boutique\/documentation\/Boutique\/AsyncStoredValue\/toggle()","conformance":{"availabilityPrefix":[{"type":"text","text":"Available when"}],"constraints":[{"type":"codeVoice","code":"Item"},{"text":" is ","type":"text"},{"code":"Bool","type":"codeVoice"},{"type":"text","text":"."}],"conformancePrefix":[{"text":"Conforms when","type":"text"}]},"title":"toggle()","kind":"symbol","type":"topic","role":"symbol","url":"\/documentation\/boutique\/asyncstoredvalue\/toggle()"},"doc://Boutique/documentation/Boutique/AsyncStoredValue/togglePresence(_:)":{"identifier":"doc:\/\/Boutique\/documentation\/Boutique\/AsyncStoredValue\/togglePresence(_:)","title":"togglePresence(_:)","abstract":[],"role":"symbol","url":"\/documentation\/boutique\/asyncstoredvalue\/togglepresence(_:)","conformance":{"availabilityPrefix":[{"type":"text","text":"Available when"}],"constraints":[{"code":"Item","type":"codeVoice"},{"type":"text","text":" conforms to "},{"type":"codeVoice","code":"Decodable"},{"text":", ","type":"text"},{"type":"codeVoice","code":"Encodable"},{"type":"text","text":", "},{"type":"codeVoice","code":"Equatable"},{"text":", and ","type":"text"},{"code":"RangeReplaceableCollection","type":"codeVoice"},{"text":".","type":"text"}],"conformancePrefix":[{"text":"Conforms when","type":"text"}]},"kind":"symbol","type":"topic","fragments":[{"kind":"keyword","text":"func"},{"kind":"text","text":" "},{"kind":"identifier","text":"togglePresence"},{"text":"<","kind":"text"},{"kind":"genericParameter","text":"Value"},{"kind":"text","text":">("},{"text":"Value","kind":"typeIdentifier"},{"kind":"text","text":") "},{"text":"async","kind":"keyword"},{"text":" ","kind":"text"},{"kind":"keyword","text":"throws"}]},"doc://Boutique/documentation/Boutique/AsyncStoredValue/set(_:)":{"kind":"symbol","url":"\/documentation\/boutique\/asyncstoredvalue\/set(_:)","type":"topic","abstract":[{"type":"text","text":"Sets a value for the @"},{"identifier":"doc:\/\/Boutique\/documentation\/Boutique\/AsyncStoredValue","type":"reference","isActive":true},{"type":"text","text":" property."}],"title":"set(_:)","role":"symbol","identifier":"doc:\/\/Boutique\/documentation\/Boutique\/AsyncStoredValue\/set(_:)","fragments":[{"text":"func","kind":"keyword"},{"text":" ","kind":"text"},{"text":"set","kind":"identifier"},{"text":"(","kind":"text"},{"text":"Item","kind":"typeIdentifier"},{"text":") ","kind":"text"},{"text":"async","kind":"keyword"},{"text":" ","kind":"text"},{"kind":"keyword","text":"throws"}]},"doc://Boutique/documentation/Boutique/AsyncStoredValue/wrappedValue":{"kind":"symbol","url":"\/documentation\/boutique\/asyncstoredvalue\/wrappedvalue","type":"topic","abstract":[{"text":"The currently stored value","type":"text"}],"title":"wrappedValue","role":"symbol","identifier":"doc:\/\/Boutique\/documentation\/Boutique\/AsyncStoredValue\/wrappedValue","fragments":[{"text":"var","kind":"keyword"},{"kind":"text","text":" "},{"kind":"identifier","text":"wrappedValue"},{"kind":"text","text":": "},{"kind":"typeIdentifier","text":"Item"}]},"doc://Boutique/documentation/Boutique/Store":{"type":"topic","fragments":[{"text":"class","kind":"keyword"},{"kind":"text","text":" "},{"text":"Store","kind":"identifier"}],"kind":"symbol","identifier":"doc:\/\/Boutique\/documentation\/Boutique\/Store","navigatorTitle":[{"text":"Store","kind":"identifier"}],"url":"\/documentation\/boutique\/store","abstract":[{"text":"A fancy persistence layer.","type":"text"}],"title":"Store","role":"symbol"},"doc://Boutique/documentation/Boutique/StoredValue":{"type":"topic","role":"symbol","fragments":[{"text":"struct","kind":"keyword"},{"kind":"text","text":" "},{"text":"StoredValue","kind":"identifier"}],"navigatorTitle":[{"text":"StoredValue","kind":"identifier"}],"identifier":"doc:\/\/Boutique\/documentation\/Boutique\/StoredValue","url":"\/documentation\/boutique\/storedvalue","kind":"symbol","title":"StoredValue","abstract":[{"text":"The @","type":"text"},{"identifier":"doc:\/\/Boutique\/documentation\/Boutique\/StoredValue","isActive":true,"type":"reference"},{"text":" property wrapper to automagically persist a single ","type":"text"},{"type":"codeVoice","code":"Item"},{"text":" in ","type":"text"},{"type":"codeVoice","code":"UserDefaults"},{"text":" ","type":"text"},{"text":"rather than an array of items that would be persisted in a ","type":"text"},{"identifier":"doc:\/\/Boutique\/documentation\/Boutique\/Store","type":"reference","isActive":true},{"text":" or using @","type":"text"},{"type":"reference","identifier":"doc:\/\/Boutique\/documentation\/Boutique\/Stored","isActive":true},{"type":"text","text":"."}]},"doc://Boutique/documentation/Boutique/AsyncStoredValue/projectedValue":{"fragments":[{"text":"var","kind":"keyword"},{"text":" ","kind":"text"},{"text":"projectedValue","kind":"identifier"},{"text":": ","kind":"text"},{"preciseIdentifier":"s:8Boutique16AsyncStoredValueV","text":"AsyncStoredValue","kind":"typeIdentifier"},{"kind":"text","text":"<"},{"text":"Item","kind":"typeIdentifier"},{"text":">","kind":"text"}],"url":"\/documentation\/boutique\/asyncstoredvalue\/projectedvalue","identifier":"doc:\/\/Boutique\/documentation\/Boutique\/AsyncStoredValue\/projectedValue","type":"topic","kind":"symbol","role":"symbol","abstract":[{"type":"text","text":"An @"},{"isActive":true,"identifier":"doc:\/\/Boutique\/documentation\/Boutique\/AsyncStoredValue","type":"reference"},{"type":"text","text":" which exposes "},{"isActive":true,"type":"reference","identifier":"doc:\/\/Boutique\/documentation\/Boutique\/AsyncStoredValue\/set(_:)"},{"type":"text","text":" and "},{"isActive":true,"type":"reference","identifier":"doc:\/\/Boutique\/documentation\/Boutique\/AsyncStoredValue\/reset()"},{"type":"text","text":" functions alongside a "},{"identifier":"doc:\/\/Boutique\/documentation\/Boutique\/AsyncStoredValue\/publisher","type":"reference","isActive":true},{"type":"text","text":"."}],"title":"projectedValue"}}}